audio_scan_info.py
audio_scan_info-0.1.1.dist-info/licenses/LICENSE
audio_scan_info-0.1.1.dist-info/METADATA
audio_scan_info-0.1.1.dist-info/WHEEL
audio_scan_info-0.1.1.dist-info/entry_points.txt
audio_scan_info-0.1.1.dist-info/top_level.txt
audio_scan_info-0.1.1.dist-info/RECORD
