Metadata-Version: 2.4
Name: audio-scan-info
Version: 0.1.1
Summary: Show metadata, tags, and stream information for audio files (MP3, FLAC)
Author: Corey Goldberg
Maintainer: Corey Goldberg
License-Expression: MIT
Project-URL: homepage, https://github.com/cgoldberg/audio-scan-info
Project-URL: source, https://github.com/cgoldberg/audio-scan-info
Project-URL: download, https://pypi.org/project/audio-scan-info
Keywords: audio,flac,metadata,mp3,music
Classifier: Environment :: Console
Classifier: Programming Language :: Python
Classifier: Programming Language :: Python :: 3
Classifier: Programming Language :: Python :: 3.12
Classifier: Programming Language :: Python :: 3.13
Classifier: Programming Language :: Python :: 3.14
Requires-Python: >=3.12
License-File: LICENSE
Requires-Dist: mutagen==1.47.0
Dynamic: license-file
